crashpad/__init__.py
crashpad/api_call.py
crashpad/django_sdk.py
crashpad/error_integration.py
crashpad/error_processing.py
crashpad-0.1.0b0.dist-info/licenses/LICENSE
crashpad-0.1.0b0.dist-info/METADATA
crashpad-0.1.0b0.dist-info/WHEEL
crashpad-0.1.0b0.dist-info/top_level.txt
crashpad-0.1.0b0.dist-info/RECORD
