Metadata-Version: 2.4
Name: crashpad
Version: 0.1.0b0
Summary: A soft landing for your Django crashes - Error tracking SDK for Django applications
Author: Crashpad Team
License-Expression: MIT
Project-URL: Homepage, https://github.com/alamin040246/crashpad
Project-URL: Repository, https://github.com/alamin040246/crashpad
Project-URL: Bug Tracker, https://github.com/alamin040246/crashpad/issues
Keywords: django,error-tracking,logging,monitoring,crash-reporting,exception-tracking
Classifier: Development Status :: 4 - Beta
Classifier: Intended Audience :: Developers
Classifier: Topic :: Software Development :: Libraries :: Python Modules
Classifier: Topic :: System :: Logging
Classifier: Programming Language :: Python :: 3
Classifier: Programming Language :: Python :: 3.6
Classifier: Programming Language :: Python :: 3.7
Classifier: Programming Language :: Python :: 3.8
Classifier: Programming Language :: Python :: 3.9
Classifier: Programming Language :: Python :: 3.10
Classifier: Programming Language :: Python :: 3.11
Classifier: Programming Language :: Python :: 3.12
Classifier: Programming Language :: Python :: 3.13
Classifier: Operating System :: OS Independent
Classifier: Framework :: Django
Classifier: Framework :: Django :: 3.2
Classifier: Framework :: Django :: 4.0
Classifier: Framework :: Django :: 4.1
Classifier: Framework :: Django :: 4.2
Classifier: Framework :: Django :: 5.0
Requires-Python: >=3.6
License-File: LICENSE
Dynamic: license-file
